ecoact_ef/__init__.py
ecoact_ef/db_model/__init__.py
ecoact_ef/domain_model/__init__.py
ecoact_ef-0.0.1.dist-info/METADATA
ecoact_ef-0.0.1.dist-info/WHEEL
ecoact_ef-0.0.1.dist-info/RECORD
